brainsbuildcode/__init__.py
brainsbuildcode/brain.py
brainsbuildcode/convert.py
brainsbuildcode-1.0.3.dist-info/LICENSE
brainsbuildcode-1.0.3.dist-info/METADATA
brainsbuildcode-1.0.3.dist-info/WHEEL
brainsbuildcode-1.0.3.dist-info/top_level.txt
brainsbuildcode-1.0.3.dist-info/RECORD
