Metadata-Version: 2.2
Name: brainsbuildcode
Version: 1.0.3
Summary: A machine learning pipeline for preprocessing, model selection, and evaluation.
Home-page: https://github.com/achelousace/brainsbuildcode
Author: Mohammad.R.AbuAyyash
Author-email: brainbuildai@gmail.com
Classifier: Programming Language :: Python :: 3
Classifier: License :: OSI Approved :: MIT License
Classifier: Operating System :: Microsoft :: Windows
Requires-Python: >=3.6
License-File: LICENSE
Requires-Dist: numpy
Requires-Dist: pandas
Requires-Dist: matplotlib
Requires-Dist: seaborn
Requires-Dist: IPython
Requires-Dist: scikit-learn
Requires-Dist: xgboost
Requires-Dist: tqdm
Dynamic: author
Dynamic: author-email
Dynamic: classifier
Dynamic: description
Dynamic: description-content-type
Dynamic: home-page
Dynamic: requires-dist
Dynamic: requires-python
Dynamic: summary
